LICENSE
MANIFEST.in
README.rst
setup.py
annotation/__init__.py
annotation/forms.py
annotation/models.py
annotation/utils.py
annotation/views.py
django_annotation.egg-info/PKG-INFO
django_annotation.egg-info/SOURCES.txt
django_annotation.egg-info/dependency_links.txt
django_annotation.egg-info/requires.txt
django_annotation.egg-info/top_level.txt