Metadata-Version: 1.1
Name: django-annotation
Version: 0.2
Summary: Basic content management.
Home-page: https://github.com/dakrauth/django-annotation
Author: David A Krauth
Author-email: dakrauth@gmail.com
License: MIT License
Platform: any
Classifier: Environment :: Web Environment
Classifier: Framework :: Django
Classifier: License :: OSI Approved :: MIT License
Classifier: Programming Language :: Python
Classifier: Programming Language :: Python :: 2.7
